api/__init__.py
api/admin.py
api/aggregate.py
api/centroids.py
api/client.py
api/cluster.py
api/datasets.py
api/documents.py
api/encoders.py
api/monitor.py
api/recommend.py
api/requests_config.py
api/search.py
api/services.py
api/tasks.py
batch/__init__.py
batch/batch_insert.py
batch/chunk.py
batch/client.py
vecdb/__init__.py
vecdb/_version.py
vecdb/base.py
vecdb/concurrency.py
vecdb/config.py
vecdb/datasets.py
vecdb/errors.py
vecdb/http_client.py
vecdb/logging.py
vecdb/progress_bar.py
vecdb/transport.py
vecdb/vecdb_config.ini
vecdb/vecdb_logging.py
vecdb/api/__init__.py
vecdb/api/admin.py
vecdb/api/aggregate.py
vecdb/api/centroids.py
vecdb/api/client.py
vecdb/api/cluster.py
vecdb/api/datasets.py
vecdb/api/documents.py
vecdb/api/encoders.py
vecdb/api/monitor.py
vecdb/api/recommend.py
vecdb/api/requests_config.py
vecdb/api/search.py
vecdb/api/services.py
vecdb/api/tasks.py
vecdb/batch/__init__.py
vecdb/batch/batch_insert.py
vecdb/batch/chunk.py
vecdb/batch/client.py
vecdb/batch/pandas_operations.py
VecDB-0.12.16.dist-info/METADATA
VecDB-0.12.16.dist-info/WHEEL
VecDB-0.12.16.dist-info/top_level.txt
VecDB-0.12.16.dist-info/RECORD
