Metadata-Version: 2.1
Name: VecDB
Version: 0.12.16
Summary: UNKNOWN
Home-page: UNKNOWN
Author: Relevance AI
Author-email: dev@vctr.ai
License: UNKNOWN
Platform: UNKNOWN
Requires-Dist: tqdm (>=4.49.0)
Requires-Dist: pandas (>=1.0.0)
Requires-Dist: loguru (>=0.5.3)
Requires-Dist: document-utils (>=1.3.0)
Requires-Dist: requests (>=2.0.0)
Requires-Dist: numpy (>=1.19.0)
Provides-Extra: dev
Requires-Dist: autopep8 ; extra == 'dev'
Requires-Dist: pylint ; extra == 'dev'
Requires-Dist: pytest ; extra == 'dev'
Requires-Dist: pytest-dotenv ; extra == 'dev'
Requires-Dist: pytest-cov ; extra == 'dev'
Requires-Dist: pytest-mock ; extra == 'dev'
Provides-Extra: excel
Requires-Dist: fsspec (==2021.10.1) ; extra == 'excel'
Requires-Dist: openpyxl (==3.0.9) ; extra == 'excel'
Provides-Extra: notebook
Requires-Dist: jsonshower ; extra == 'notebook'
Provides-Extra: tests
Requires-Dist: pytest ; extra == 'tests'
Requires-Dist: fsspec (==2021.10.1) ; extra == 'tests'
Requires-Dist: openpyxl (==3.0.9) ; extra == 'tests'
